{
  "type": "AreaChart",
  "displayed": false,
  "data": {
    "cols": [
      {
        "id": "month",
        "label": "Month",
        "type": "string",
        "p": {}
      },
      {
        "id": "laptop-id",
        "label": "Java",
        "type": "number",
        "p": {}
      },
      {
        "id": "desktop-id",
        "label": "CSS",
        "type": "number",
        "p": {}
      },
      {
        "id": "server-id",
        "label": "HTML",
        "type": "number",
        "p": {}
      },
      {
        "id": "cost-id",
        "label": "JavaScript",
        "type": "number"
      }
    ],
    "rows": [
       {
        "c": [
          {
            "v": "January"
          },
          {
            "v": 5,
            "f": "42 items"
          },
          {
            "v": 2,
            "f": "Ony 12 items"
          },
          {
            "v": 7,
            "f": "7 servers"
          },
          {
            "v": 15
          }
        ]
      },
      {
        "c": [
          {
            "v": "February"
          },
          {
            "v": 19,
            "f": "42 items"
          },
          {
            "v": 12,
            "f": "Ony 12 items"
          },
          {
            "v": 7,
            "f": "7 servers"
          },
          {
            "v": 4
          }
        ]
      },
      {
        "c": [
          {
            "v": "March"
          },
          {
            "v": 8,
            "f": "42 items"
          },
          {
            "v": 12,
            "f": "Ony 12 items"
          },
          {
            "v": 7,
            "f": "7 servers"
          },
          {
            "v": 4
          }
        ]
      }
    ]
  },
  "options": {
    "backgroundColor": { "fill":"transparent" },
    "colors": ["#fa8564", "#f4d66c", "#8491c7", "#aec785"],
    "title": "Sales per month",
    "isStacked": "true",
    "fill": 20,
    "displayExactValues": true,
    "vAxis": {
      "gridlines": {
        "count": 10
      }
    }
  },
  "formatters": {}
}